nomad_plugins/__init__.py
nomad_plugins/plugin_crawler.py
nomad_plugins/apps/__init__.py
nomad_plugins/schema_packages/__init__.py
nomad_plugins/schema_packages/plugin.py
nomad_plugins-0.1.3.dist-info/LICENSE
nomad_plugins-0.1.3.dist-info/METADATA
nomad_plugins-0.1.3.dist-info/WHEEL
nomad_plugins-0.1.3.dist-info/entry_points.txt
nomad_plugins-0.1.3.dist-info/top_level.txt
nomad_plugins-0.1.3.dist-info/RECORD
