Metadata-Version: 2.1
Name: nomad-plugins
Version: 0.1.3
Summary: A plugin for discovering other plugins.
Author-email: Hampus Näsström <hampus.naesstroem@physik.hu-berlin.de>
Maintainer-email: Hampus Näsström <hampus.naesstroem@physik.hu-berlin.de>
License: 
Project-URL: Repository, https://github.com/hampusnasstrom/nomad-plugins
Classifier: Intended Audience :: Developers
Classifier: Operating System :: OS Independent
Classifier: Programming Language :: Python
Classifier: Programming Language :: Python :: 3.9
Classifier: Programming Language :: Python :: 3.10
Classifier: Programming Language :: Python :: 3.11
Classifier: Programming Language :: Python :: 3.12
Classifier: License :: OSI Approved :: Apache Software License
Requires-Python: >=3.9
License-File: LICENSE
Requires-Dist: nomad-lab>=1.3.0
Requires-Dist: python-magic-bin; sys_platform == "win32"
Requires-Dist: toml
Requires-Dist: click
Requires-Dist: requests
Provides-Extra: dev
Requires-Dist: ruff; extra == "dev"
Requires-Dist: pytest; extra == "dev"
Requires-Dist: structlog; extra == "dev"
